tm_simulator/__init__.py
tm_simulator/cli.py
tm_simulator/core.py
tm_simulator/tm.py
tm_simulator-0.1.2.dist-info/METADATA
tm_simulator-0.1.2.dist-info/WHEEL
tm_simulator-0.1.2.dist-info/entry_points.txt
tm_simulator-0.1.2.dist-info/top_level.txt
tm_simulator-0.1.2.dist-info/RECORD
