Metadata-Version: 2.4
Name: tm-simulator
Version: 0.1.2
Summary: A small example package
Author: TheVideoFelix
Classifier: Programming Language :: Python :: 3
Classifier: Operating System :: OS Independent
Requires-Python: >=3.13.7
Requires-Dist: requests
